{ "localReadings": [
{ "instance" : 101, "time" : "Sun Feb 16 09:26:41 2020", "light" :  84, "temp" : 69.8, "humidity" : 20 },
{ "instance" : 101, "time" : "Sun Feb 16 09:26:48 2020", "light" :  84, "temp" : 69.8, "humidity" : 20 },
{ "instance" : 101, "time" : "Sun Feb 16 09:26:55 2020", "light" :  85, "temp" : 69.8, "humidity" : 20 },
{ "instance" : 101, "time" : "Sun Feb 16 09:27:02 2020", "light" :  85, "temp" : 69.8, "humidity" : 20 },
{ "instance" : 101, "time" : "Sun Feb 16 09:27:09 2020", "light" :  84, "temp" : 69.8, "humidity" : 20 },
{ "instance" : 101, "time" : "Sun Feb 16 09:27:16 2020", "light" :  85, "temp" : 69.8, "humidity" : 20 },
{ "instance" : 101, "time" : "Sun Feb 16 09:27:23 2020", "light" :  85, "temp" : 69.8, "humidity" : 20 },
{ "instance" : 101, "time" : "Sun Feb 16 09:27:30 2020", "light" :  85, "temp" : 69.8, "humidity" : 20 },
{ "instance" : 101, "time" : "Sun Feb 16 09:27:36 2020", "light" :  85, "temp" : 69.8, "humidity" : 20 },
{ "instance" : 101, "time" : "Sun Feb 16 09:27:43 2020", "light" :  86, "temp" : 69.8, "humidity" : 20 },
{ "instance" : 101, "time" : "Sun Feb 16 09:27:50 2020", "light" :  87, "temp" : 69.8, "humidity" : 20 },
{ "instance" : 101, "time" : "Sun Feb 16 09:27:57 2020", "light" :  87, "temp" : 69.8, "humidity" : 20 },
{ "instance" : 101, "time" : "Sun Feb 16 09:28:04 2020", "light" :  89, "temp" : 69.8, "humidity" : 20 },
{ "instance" : 101, "time" : "Sun Feb 16 09:28:11 2020", "light" :  88, "temp" : 69.8, "humidity" : 20 },
{ "instance" : 101, "time" : "Sun Feb 16 09:28:18 2020", "light" :  90, "temp" : 69.8, "humidity" : 20 },
{ "instance" : 101, "time" : "Sun Feb 16 09:28:25 2020", "light" :  89, "temp" : 69.8, "humidity" : 20 },
{ "instance" : 101, "time" : "Sun Feb 16 09:28:32 2020", "light" :  90, "temp" : 69.8, "humidity" : 20 },
{ "instance" : 101, "time" : "Sun Feb 16 09:28:39 2020", "light" :  90, "temp" : 69.8, "humidity" : 20 },
{ "instance" : 101, "time" : "Sun Feb 16 09:28:46 2020", "light" :  91, "temp" : 69.8, "humidity" : 20 },
{ "instance" : 101, "time" : "Sun Feb 16 09:28:52 2020", "light" :  91, "temp" : 69.8, "humidity" : 20 },
{ "instance" : 101, "time" : "Sun Feb 16 09:28:59 2020", "light" :  92, "temp" : 69.8, "humidity" : 20 },
{ "instance" : 101, "time" : "Sun Feb 16 09:29:06 2020", "light" :  92, "temp" : 69.8, "humidity" : 20 }
]}